ipsluna/__init__.py
ipsluna/ips/__init__.py
ipsluna-0.72.dist-info/LICENSE
ipsluna-0.72.dist-info/METADATA
ipsluna-0.72.dist-info/WHEEL
ipsluna-0.72.dist-info/top_level.txt
ipsluna-0.72.dist-info/RECORD
