Metadata-Version: 2.1
Name: ipsluna
Version: 0.72
Summary: Deep IPS Filetype Handler
Home-page: https://github.com/BrettefromNesUniverse/ipsluna
Author: Brette
Author-email: benissoflippinghot@gmail.com
Project-URL: Bug Tracker, https://github.com/BrettefromNesUniverse/ipsluna/issues
Project-URL: Discord, https://discord.gg/3DYCru4dCV
Classifier: Programming Language :: Python :: 3
Classifier: License :: OSI Approved :: MIT License
Classifier: Operating System :: OS Independent
Requires-Python: >=3.6
License-File: LICENSE
